CYPHER_PROTOCOL/__init__.py
CYPHER_PROTOCOL/CYPHER_CLIENT/__init__.py
CYPHER_PROTOCOL/CYPHER_CLIENT/cypher_client.py
CYPHER_PROTOCOL/CYPHER_CLIENT/FTP/__init__.py
CYPHER_PROTOCOL/CYPHER_CLIENT/FTP/ftp_client.py
CYPHER_PROTOCOL/CYPHER_SERVER/__init__.py
CYPHER_PROTOCOL/CYPHER_SERVER/cypher_server.py
CYPHER_PROTOCOL/CYPHER_SERVER/FTP/__init__.py
CYPHER_PROTOCOL/CYPHER_SERVER/FTP/ftp_server.py
cypher_protocol_P_Y_R_O_B_O_T-1.5.0.dist-info/LICENSE
cypher_protocol_P_Y_R_O_B_O_T-1.5.0.dist-info/METADATA
cypher_protocol_P_Y_R_O_B_O_T-1.5.0.dist-info/WHEEL
cypher_protocol_P_Y_R_O_B_O_T-1.5.0.dist-info/top_level.txt
cypher_protocol_P_Y_R_O_B_O_T-1.5.0.dist-info/RECORD
