Metadata-Version: 2.1
Name: cypher-protocol-P-Y-R-O-B-O-T
Version: 1.5.0
Summary: A COMMUNICATION PROTOCOL FOR COMPUTERS TO COMMUNICATE THROUGH A SAFE CHANNEL
Author-email: KUSHAL <NONE@NONE.com>
License: GNU GENERAL PUBLIC LICENSE
Project-URL: Homepage, https://github.com/P-Y-R-O-B-O-T/CYPHER_PROTOCOL
Keywords: protocol,comminication,tcp,http Alternative,cypher,cypher_protocol,networking,newwork,network programming,multithreaded,server,client,multithreading
Requires-Python: >=3.10
License-File: LICENSE
Requires-Dist: cryptography
